<?xml version="1.0" encoding="UTF-8"?>
<!--
  **************************************************-
  Ingrid Portal Apps
  ==================================================
  Copyright (C) 2014 wemove digital solutions GmbH
  ==================================================
  Licensed under the EUPL, Version 1.1 or – as soon they will be
  approved by the European Commission - subsequent versions of the
  EUPL (the "Licence");
  
  You may not use this work except in compliance with the Licence.
  You may obtain a copy of the Licence at:
  
  http://ec.europa.eu/idabc/eupl5
  
  Unless required by applicable law or agreed to in writing, software
  distributed under the Licence is distributed on an "AS IS" basis,
  WITHOUT WARRANTIES OR CONDITIONS OF ANY KIND, either express or implied.
  See the Licence for the specific language governing permissions and
  limitations under the Licence.
  **************************************************#
  -->

<profile>
    <name>mu_ni</name>
    <description>Portal-Profile für das Ministerium für Umwelt Niedersachsen</description>
    <pages>
        <page>
            <name>main-service.psml</name>
            <hidden>true</hidden>
        </page>
        <page>
            <name>mdek/mdek_portal_admin.psml</name>
            <hidden>true</hidden>
        </page>
        <page>
            <name>main-features.psml</name>
            <hidden>true</hidden>
        </page>
        <page>
            <name>main-maps.psml</name>
            <hidden>true</hidden>
        </page>
        <page>
            <name>_role/user/myportal-edit-account.psml</name>
            <hidden>false</hidden>
            <portlets>
                <portlet col="0" row="0">
                    <name>ingrid-portal-apps::MyPortalEditAccountPortlet</name>
                </portlet>
                <portlet col="1" row="0">
                    <name>ingrid-portal-apps::MyPortalEditAboutInfoPortlet</name>
                </portlet>
                <portlet col="1" row="1">
                    <name>ingrid-portal-apps::MyPortalEditAdvancedInfoPortlet</name>
                </portlet>
            </portlets>
        </page>
        <page>
            <name>default-page.psml</name>
            <hidden>false</hidden>
            <portlets>
                <portlet col="0" row="0">
                    <name>ingrid-portal-apps::SearchSimple</name>
                </portlet>
                <portlet col="0" row="1">
                    <name>ingrid-portal-apps::EnvironmentTeaser</name>
                </portlet>
                <portlet col="0" row="2">
                    <name>ingrid-portal-apps::RssNewsTeaser</name>
                </portlet>
                <portlet col="1" row="0">
                    <name>ingrid-portal-apps::IngridInformPortlet</name>
                </portlet>
                <portlet col="1" row="1">
                    <name>ingrid-portal-apps::MeasuresTeaser</name>
                </portlet>
                <portlet col="1" row="2">
                    <name>ingrid-portal-apps::ChronicleTeaser</name>
                </portlet>
            </portlets>
        </page>
        <page>
            <name>_role/user/default-page.psml</name>
            <hidden>false</hidden>
            <portlets>
                <portlet col="0" row="0">
                    <name>ingrid-portal-apps::SearchSimple</name>
                </portlet>
                <portlet col="0" row="1">
                    <name>ingrid-portal-apps::EnvironmentTeaser</name>
                </portlet>
                <portlet col="0" row="2">
                    <name>ingrid-portal-apps::RssNewsTeaser</name>
                </portlet>
                <portlet col="1" row="0">
                    <name>ingrid-portal-apps::IngridInformPortlet</name>
                </portlet>
                <portlet col="1" row="1">
                    <name>ingrid-portal-apps::MeasuresTeaser</name>
                </portlet>
                <portlet col="1" row="2">
                    <name>ingrid-portal-apps::ChronicleTeaser</name>
                </portlet>
            </portlets>
        </page>
        <page>
            <name>_user/template/default-page.psml</name>
            <hidden>false</hidden>
            <portlets>
                <portlet col="0" row="0">
                    <name>ingrid-portal-apps::SearchSimple</name>
                </portlet>
                <portlet col="0" row="1">
                    <name>ingrid-portal-apps::EnvironmentTeaser</name>
                </portlet>
                <portlet col="0" row="2">
                    <name>ingrid-portal-apps::RssNewsTeaser</name>
                </portlet>
                <portlet col="1" row="0">
                    <name>ingrid-portal-apps::IngridInformPortlet</name>
                </portlet>
                <portlet col="1" row="1">
                    <name>ingrid-portal-apps::MeasuresTeaser</name>
                </portlet>
                <portlet col="1" row="2">
                    <name>ingrid-portal-apps::ChronicleTeaser</name>
                </portlet>
            </portlets>
        </page>
        <page>
            <name>search-catalog/search-catalog-hierarchy.psml</name>
            <hidden>true</hidden>
        </page>
        <page>
            <name>service-contact-newsletter.psml</name>
            <hidden>true</hidden>
        </page>
    </pages>
    <files>
        <file>
            <action>copy-dir</action>
            <src>ingrid-portal/</src>
        </file>
        <file>
            <action>copy-dir</action>
            <src>ingrid-portal-apps/</src>
        </file>
        <file>
            <action>copy-dir</action>
            <src>ingrid-portal-mdek/</src>
        </file>
    </files>
    <sql>
    	<!-- Use old templates for info portlet -->
       	<execute>
            <![CDATA[UPDATE fragment_pref_value SET value='/WEB-INF/templates/chronicle_info.vm' WHERE value='/WEB-INF/templates/chronicle_info_new.vm']]>
        </execute>
        <execute>
            <![CDATA[UPDATE fragment_pref_value SET value='/WEB-INF/templates/environment_info.vm' WHERE value='/WEB-INF/templates/environment_info_new.vm']]>
        </execute>
        <execute>
            <![CDATA[UPDATE fragment_pref_value SET value='/WEB-INF/templates/measures_info.vm' WHERE value='/WEB-INF/templates/measures_info_new.vm']]>
        </execute>
        <execute>
            <![CDATA[UPDATE fragment_pref_value SET value='/WEB-INF/templates/service_info.vm' WHERE value='/WEB-INF/templates/service_info_new.vm']]>
        </execute>
        <execute>
            <![CDATA[UPDATE fragment_pref_value SET value='/WEB-INF/templates/search_simple_info.vm' WHERE value='/WEB-INF/templates/search_simple_info_new.vm']]>
        </execute>
        <!-- Set decorator to ingrid-marginal-teaser -->
        <execute>
            <![CDATA[CREATE TABLE tmp_table (item_key VARCHAR2(255 CHAR) DEFAULT NULL\, item_value VARCHAR2(255 CHAR) DEFAULT NULL\, item_date TIMESTAMP DEFAULT CURRENT_TIMESTAMP NOT NULL)]]>
        </execute>
        <execute>
            <![CDATA[INSERT INTO tmp_table (item_key\, item_value) values ('tmp_id'\, '0')]]>
        </execute>
        <execute>
            <![CDATA[UPDATE tmp_table SET item_value = (SELECT fragment_id FROM fragment WHERE page_id = (SELECT page_id FROM page WHERE path = '/main-chronicle.psml')) WHERE item_key='tmp_id']]>
        </execute>
        <execute>
            <![CDATA[UPDATE fragment SET decorator='ingrid-marginal-teaser' WHERE parent_id = (SELECT item_value FROM tmp_table WHERE item_key = 'tmp_id') AND name = 'ingrid-portal-apps::InfoPortlet']]>
        </execute>
        <execute>
            <![CDATA[UPDATE tmp_table SET item_value = (SELECT fragment_id FROM fragment WHERE page_id = (SELECT page_id FROM page WHERE path = '/main-measures.psml')) WHERE item_key='tmp_id']]>
        </execute>
        <execute>
            <![CDATA[UPDATE fragment SET decorator='ingrid-marginal-teaser' WHERE parent_id = (SELECT item_value FROM tmp_table WHERE item_key = 'tmp_id') AND name = 'ingrid-portal-apps::InfoPortlet']]>
        </execute>
        <execute>
            <![CDATA[UPDATE tmp_table SET item_value = (SELECT fragment_id FROM fragment WHERE page_id = (SELECT page_id FROM page WHERE path = '/main-environment.psml')) WHERE item_key='tmp_id']]>
        </execute>
        <execute>
            <![CDATA[UPDATE fragment SET decorator='ingrid-marginal-teaser' WHERE parent_id = (SELECT item_value FROM tmp_table WHERE item_key = 'tmp_id') AND name = 'ingrid-portal-apps::InfoPortlet']]>
        </execute>
        <execute>
            <![CDATA[UPDATE tmp_table SET item_value = (SELECT fragment_id FROM fragment WHERE page_id = (SELECT page_id FROM page WHERE path = '/main-service.psml')) WHERE item_key='tmp_id']]>
        </execute>
        <execute>
            <![CDATA[UPDATE fragment SET decorator = 'ingrid-marginal-teaser' WHERE parent_id = (SELECT item_value FROM tmp_table WHERE item_key = 'tmp_id') AND name = 'ingrid-portal-apps::InfoPortlet']]>
        </execute>
        <execute>
            <![CDATA[UPDATE tmp_table SET item_value = (SELECT fragment_id FROM fragment WHERE page_id = (SELECT page_id FROM page WHERE path = '/main-search.psml')) WHERE item_key='tmp_id']]>
        </execute>
        <execute>
            <![CDATA[INSERT INTO ingrid_lookup (item_key\, item_value) values ('tmp_id'\, '0')]]>
        </execute>
        <execute>
            <![CDATA[UPDATE ingrid_lookup SET item_value = (SELECT fragment_id FROM fragment WHERE parent_id = (SELECT item_value FROM tmp_table WHERE item_key = 'tmp_id') AND name = 'jetspeed-layouts::IngridTwoColumns') WHERE item_key='tmp_id']]>
        </execute>
        <execute>
            <![CDATA[UPDATE fragment SET decorator = 'ingrid-marginal-teaser' WHERE parent_id = (SELECT item_value FROM ingrid_lookup WHERE item_key = 'tmp_id') AND name = 'ingrid-portal-apps::InfoPortlet']]>
        </execute>
        <execute>
            <![CDATA[DELETE FROM ingrid_lookup WHERE item_key = 'tmp_id']]>
        </execute>
        <!-- Revert feature page as default for about page -->
        <execute>
            <![CDATA[UPDATE tmp_table SET item_value = (SELECT menu_id FROM folder_menu WHERE name = 'main-menu') WHERE item_key='tmp_id']]>
        </execute>
        <execute>
            <![CDATA[UPDATE folder_menu SET OPTIONS = '/main-about.psml' WHERE OPTIONS = '/main-features.psml' AND parent_id  = (SELECT item_value FROM tmp_table WHERE item_key = 'tmp_id') ]]>
        </execute>
        <execute>
            <![CDATA[DROP TABLE tmp_table]]>
        </execute>
        <execute>
            <![CDATA[UPDATE page SET title = 'ingrid.page.features.tooltip'\, short_title = 'ingrid.page.features' WHERE path = '/main-features.psml']]>
        </execute>
    </sql>
</profile>
