<?xml version="1.0" encoding="ISO-8859-1"?>
<!DOCTYPE hibernate-mapping PUBLIC "-//Hibernate/Hibernate Mapping DTD 3.0//EN" "http://hibernate.sourceforge.net/hibernate-mapping-3.0.dtd">

<hibernate-mapping>
  	<class name="de.ingrid.portal.om.IngridRSSStore" table="ingrid_rss_store">
		<id name="id" column="link" type="java.lang.String">
    		<generator class="assigned"/>
        </id>
    	<property name="link" type="java.lang.String" insert="false" update="false"/>
    	<property name="author" type="java.lang.String"/>
    	<property name="categories" type="java.lang.String"/>
    	<property name="copyright" type="java.lang.String"/>
    	<property name="description" type="java.lang.String"/>
    	<property name="language" type="java.lang.String"/>
    	<property name="publishedDate" type="java.sql.Date" column="published_date"/>
    	<property name="title" type="java.lang.String"/>
  </class>
</hibernate-mapping>
