<?xml version="1.0" encoding="UTF-8"?>
<!DOCTYPE beans PUBLIC "-//SPRING//DTD BEAN//EN" "http://www.springframework.org/dtd/spring-beans.dtd">
<!--
    Database PSML Manager Interception for handling Cache Rollback
    We also have examples here of replay interception for failover to 
    a second database on update failures
   -->    
<beans>

<!--
  WEMOVE:
  This is needed for the configuration of the Datatbase Page Manager (PSML in Database !)
  This file was copied from
  jetspeed/WEB-INF/assembly/alternate/interceptors.xml
  to here.
  see mail "Re: Storing PSML in Database", Donnerstag, 9. März 2006 18:04 from Jetspeed List.
-->

    <bean id="pageManagerInterceptor" class="org.apache.jetspeed.util.interceptors.PageManagerInterceptor">
    </bean>


    <bean id="PageManagerTransactionProxy" class="org.springframework.transaction.interceptor.TransactionProxyFactoryBean"
                        abstract="true">
        <property name="transactionManager"><ref bean="transactionManager"/></property>
        <property name="transactionAttributes">
            <props>
                <prop key="*">PROPAGATION_REQUIRED</prop>
            </props>
        </property>
        <property name="preInterceptors"> 
            <list>
                <ref local="pageManagerInterceptor" />
            </list>
        </property>
    </bean>

    <!--    
        Replay support:
        
    <bean id="replayTransactionProxy" class="org.springframework.transaction.interceptor.TransactionProxyFactoryBean"
                        abstract="true">
        <property name="transactionManager"><ref bean="transactionManager"/></property>
        <property name="transactionAttributes">
            <props>
                <prop key="*">PROPAGATION_REQUIRED</prop>
            </props>
        </property>
        <property name="preInterceptors"> 
            <list>
                <ref local="methodReplayInterceptor" />
            </list>
        </property>
    </bean>
        
   <bean id="replayDecisionMakerBean"
        class="org.apache.jetspeed.util.interceptors.TransactionalMethodReplayDecisionMaker">
        <property name="sqlErrorCodes">
            <value>9999, 400, -80</value> 
             <value>9999</value>
        </property>
    </bean>

    <bean id="methodReplayInterceptor" class="org.apache.jetspeed.util.interceptors.MethodReplayInterceptor">
        <property name="retryCount">
            <value>3</value>
        </property>
        <property name="retryInterval">
            <value>500</value></property>  retry every 500 milliseconds 
        <property name="replayDecisionMaker">
            <ref bean="replayDecisionMakerBean"/>
        </property>
    </bean>
 -->
            
</beans>
